micro_benchmark/__init__.py
micro_benchmark/code.py
micro_benchmark/constants.py
micro_benchmark/decorators.py
micro_benchmark/examples.py
micro_benchmark/runtime.py
egenix_micro_benchmark-0.1.0.dist-info/LICENSE
egenix_micro_benchmark-0.1.0.dist-info/METADATA
egenix_micro_benchmark-0.1.0.dist-info/WHEEL
egenix_micro_benchmark-0.1.0.dist-info/top_level.txt
egenix_micro_benchmark-0.1.0.dist-info/RECORD
